{"tracedFiles":[".classpath","etc/nodeInfo.xml","src/main/i5/las2peer/services/test1234/Test1234.java",".project","etc/ivy/ivy.xml","README.md","src/test/i5/las2peer/services/test1234/Test1234Test.java","etc/i5.las2peer.services.test1234.Test1234.properties","etc/ant_configuration/service.properties","etc/i5.las2peer.webConnector.WebConnector.properties","bin/start_network.bat","build.xml","bin/start_network.sh"],"id":"817b5d20-bc30-41af-a7fc-d6e991805bc4","modelsToFile":{"31b5c0c7b06a4b11de58db33":{"files":["src/main/i5/las2peer/services/test1234/Test1234.java"]},"31b5c0c7b06a4b11de58db33:servicePropertiesFile":{"files":["etc/i5.las2peer.services.test1234.Test1234.properties"]}}}